shsim/__init__.py
shsim/core.py
shsim-0.2.0.dist-info/licenses/LICENSE
shsim-0.2.0.dist-info/METADATA
shsim-0.2.0.dist-info/WHEEL
shsim-0.2.0.dist-info/top_level.txt
shsim-0.2.0.dist-info/RECORD
