Metadata-Version: 2.4
Name: shsim
Version: 0.2.0
Summary: Tiny cross-OS shell-like helpers for Python
Author: 4everstella
License: MIT License
Project-URL: Homepage, https://github.com/4everstella/shsim
Classifier: Programming Language :: Python :: 3
Classifier: License :: OSI Approved :: MIT License
Classifier: Operating System :: OS Independent
Classifier: Programming Language :: Python :: 3
Classifier: Programming Language :: Python :: 3 :: Only
Classifier: Programming Language :: Python :: 3.10
Classifier: Programming Language :: Python :: 3.11
Classifier: Programming Language :: Python :: 3.12
Requires-Python: >=3.10
License-File: LICENSE
Dynamic: license-file
